lucas_helpers_webforce/__init__.py
lucas_helpers_webforce/bus_events.py
lucas_helpers_webforce/call.py
lucas_helpers_webforce/call_event_log.py
lucas_helpers_webforce/conference_event_log.py
lucas_helpers_webforce/database.py
lucas_helpers_webforce/events.py
lucas_helpers_webforce/functions.py
lucas_helpers_webforce/libraries.py
lucas_helpers_webforce/models.py
lucas_helpers_webforce/mysql.py
lucas_helpers_webforce/queues.py
lucas_helpers_webforce/rabbit.py
lucas_helpers_webforce/timezones.py
lucas_helpers_webforce-0.4.9.dist-info/METADATA
lucas_helpers_webforce-0.4.9.dist-info/WHEEL
lucas_helpers_webforce-0.4.9.dist-info/top_level.txt
lucas_helpers_webforce-0.4.9.dist-info/RECORD
